{
  "name": "BankAccount",
  "fields": [
    {
      "fieldName": "name",
      "fieldType": "String",
      "fieldValidateRules": ["required"]
    },
    {
      "fieldName": "balance",
      "fieldType": "BigDecimal",
      "fieldValidateRules": ["required"]
    }
  ],
  "relationships": [
    {
      "relationshipType": "one-to-many",
      "otherEntityName": "operation",
      "otherEntityRelationshipName": "bankAccount",
      "relationshipName": "operation"
    },
    {
      "relationshipType": "many-to-one",
      "otherEntityName": "user",
      "otherEntityRelationshipName": "bankAccount",
      "relationshipName": "user",
      "otherEntityField": "login"
    }
  ],
  "changelogDate": "20210410173425",
  "entityTableName": "bank_account",
  "dto": "no",
  "pagination": "no",
  "service": "no",
  "jpaMetamodelFiltering": false,
  "fluentMethods": true,
  "readOnly": false,
  "embedded": false,
  "clientRootFolder": "",
  "applications": ["JhipsterSampleApplication"]
}
